{
  "id": "dashboards",
  "title": "Dashboards",
  "description": "Build cross-functional monitoring views that combine metrics, traces, and KPIs.",
  "source": "@site/docs/rightsight/dashboards.md",
  "sourceDirName": ".",
  "slug": "/dashboards",
  "permalink": "/rightsight/dashboards",
  "draft": false,
  "unlisted": false,
  "editUrl": "https://github.com/GetRightData/docs/edit/main/docs/rightsight/dashboards.md",
  "tags": [
    {
      "inline": true,
      "label": "rightsight",
      "permalink": "/rightsight/tags/rightsight"
    },
    {
      "inline": true,
      "label": "dashboards",
      "permalink": "/rightsight/tags/dashboards"
    }
  ],
  "version": "current",
  "lastUpdatedBy": "Anil Pulugujja",
  "lastUpdatedAt": 1772042444000,
  "frontMatter": {
    "title": "Dashboards",
    "description": "Build cross-functional monitoring views that combine metrics, traces, and KPIs.",
    "sidebar_label": "Dashboards",
    "tags": [
      "rightsight",
      "dashboards"
    ]
  },
  "sidebar": "rightsightSidebar",
  "previous": {
    "title": "AI Enrichment",
    "permalink": "/rightsight/ai-enrichment"
  },
  "next": {
    "title": "Configuration",
    "permalink": "/rightsight/configuration"
  }
}